fastcs_jungfrau/__init__.py
fastcs_jungfrau/__main__.py
fastcs_jungfrau/_version.py
fastcs_jungfrau/jungfrau_controller.py
fastcs_jungfrau-0.1.0b6.dist-info/licenses/LICENSE
fastcs_jungfrau-0.1.0b6.dist-info/METADATA
fastcs_jungfrau-0.1.0b6.dist-info/WHEEL
fastcs_jungfrau-0.1.0b6.dist-info/entry_points.txt
fastcs_jungfrau-0.1.0b6.dist-info/top_level.txt
fastcs_jungfrau-0.1.0b6.dist-info/RECORD
